<?xml version="1.0" encoding="utf-8" ?>
<dwsync>
<file name="jquery-ui.css" server="10.47.1.4//var/www/html/mik-controller/mikrotik/" local="132390046685308107" remote="132392501890000000" Dst="0" />
<file name="jquery-ui.js" server="10.47.1.4//var/www/html/mik-controller/mikrotik/" local="132390046685328100" remote="132392501890000000" Dst="0" />
<file name="jquery-ui.min.css" server="10.47.1.4//var/www/html/mik-controller/mikrotik/" local="132390046685338101" remote="132392501890000000" Dst="0" />
<file name="jquery-ui.min.js" server="10.47.1.4//var/www/html/mik-controller/mikrotik/" local="132390046685348094" remote="132392501900000000" Dst="0" />
<file name="jquery-ui.structure.css" server="10.47.1.4//var/www/html/mik-controller/mikrotik/" local="132390046685358091" remote="132392501900000000" Dst="0" />
<file name="jquery-ui.structure.min.css" server="10.47.1.4//var/www/html/mik-controller/mikrotik/" local="132390046685358091" remote="132392501900000000" Dst="0" />
<file name="jquery-ui.theme.css" server="10.47.1.4//var/www/html/mik-controller/mikrotik/" local="132390046685358091" remote="132392501900000000" Dst="0" />
<file name="jquery-ui.theme.min.css" server="10.47.1.4//var/www/html/mik-controller/mikrotik/" local="132390046685368087" remote="132392501910000000" Dst="0" />
<file name="LICENSE.txt" server="10.47.1.4//var/www/html/mik-controller/mikrotik/" local="132390046685278116" remote="132392501910000000" Dst="0" />
</dwsync>